model_evaluation/__init__.py
model_evaluation/stoi_pesq.py
model_evaluation_777-1.0.2.dist-info/LICENSE
model_evaluation_777-1.0.2.dist-info/WHEEL
model_evaluation_777-1.0.2.dist-info/METADATA
model_evaluation_777-1.0.2.dist-info/RECORD
