Metadata-Version: 2.1
Name: model-evaluation-777
Version: 1.0.2
Summary: Evaluate speech enhancemnt model performance
Author: Chengwei Ouyang
Author-email: chengwei@evocolabs.com
Requires-Python: >=3.7,<4.0
Classifier: Programming Language :: Python :: 3
Classifier: Programming Language :: Python :: 3.7
Classifier: Programming Language :: Python :: 3.8
Classifier: Programming Language :: Python :: 3.9
Requires-Dist: librosa (>=0.8.1,<0.9.0)
Requires-Dist: numpy (>=1.21.0,<2.0.0)
Requires-Dist: pesq (>=0.0.3,<0.0.4)
Requires-Dist: pystoi (>=0.3.3,<0.4.0)
